py_admetricks/__init__.py
py_admetricks/pymetricks.py
py_metricks-0.0.3.dist-info/LICENSE
py_metricks-0.0.3.dist-info/METADATA
py_metricks-0.0.3.dist-info/WHEEL
py_metricks-0.0.3.dist-info/top_level.txt
py_metricks-0.0.3.dist-info/RECORD
