Metadata-Version: 2.1
Name: py-metricks
Version: 0.0.3
Summary: Simplification of the connection to the Admetricks REST API in Python.
Home-page: UNKNOWN
Author: Carlangastr
License: UNKNOWN
Keywords: python,admetricks,sql,marketing,audience
Platform: UNKNOWN
Classifier: Development Status :: 1 - Planning
Classifier: Intended Audience :: Developers
Classifier: Programming Language :: Python :: 3
Classifier: Operating System :: Unix
Classifier: Operating System :: MacOS :: MacOS X
Classifier: Operating System :: Microsoft :: Windows
Requires-Dist: pandas
Requires-Dist: ftfy
Requires-Dist: requests
Requires-Dist: unidecode
